{
  "version": 2,
  "extractor": "papercropper",
  "tables": [
    {
      "url": "assets/tables/arxiv/2606.05484v1/table-001.webp",
      "caption": "",
      "page": 0,
      "index": 1,
      "width": 1452,
      "height": 527,
      "label": "Table"
    },
    {
      "url": "assets/tables/arxiv/2606.05484v1/table-002.webp",
      "caption": "",
      "page": 0,
      "index": 2,
      "width": 1459,
      "height": 645,
      "label": "Table"
    },
    {
      "url": "assets/tables/arxiv/2606.05484v1/table-003.webp",
      "caption": "",
      "page": 0,
      "index": 3,
      "width": 1466,
      "height": 548,
      "label": "Table"
    },
    {
      "url": "assets/tables/arxiv/2606.05484v1/table-004.webp",
      "caption": "",
      "page": 0,
      "index": 4,
      "width": 1382,
      "height": 279,
      "label": "Table"
    },
    {
      "url": "assets/tables/arxiv/2606.05484v1/table-005.webp",
      "caption": "",
      "page": 0,
      "index": 5,
      "width": 1310,
      "height": 610,
      "label": "Table"
    },
    {
      "url": "assets/tables/arxiv/2606.05484v1/table-006.webp",
      "caption": "",
      "page": 0,
      "index": 6,
      "width": 1041,
      "height": 186,
      "label": "Table"
    },
    {
      "url": "assets/tables/arxiv/2606.05484v1/table-007.webp",
      "caption": "",
      "page": 0,
      "index": 7,
      "width": 911,
      "height": 455,
      "label": "Table"
    },
    {
      "url": "assets/tables/arxiv/2606.05484v1/table-008.webp",
      "caption": "",
      "page": 0,
      "index": 8,
      "width": 1214,
      "height": 318,
      "label": "Table"
    },
    {
      "url": "assets/tables/arxiv/2606.05484v1/table-009.webp",
      "caption": "",
      "page": 0,
      "index": 9,
      "width": 1472,
      "height": 905,
      "label": "Table"
    }
  ]
}